[
  {
    "id": "a1b2c3d4-0001-4000-8000-000000000001",
    "nombre": "Paella valenciana",
    "categoria": "arroces",
    "sabor": "salado",
    "tiempoPreparacion": 60,
    "favorita": false,
    "imagen": "https://images.unsplash.com/photo-1534080564583-6be75777b70a?w=800&q=80&crop=entropy",
    "ingredientes": [
      { "nombre": "arroz bomba", "cantidad": 400, "unidad": "g", "familia": "cereales" },
      { "nombre": "pollo", "cantidad": 500, "unidad": "g", "familia": "carnes" },
      { "nombre": "conejo", "cantidad": 400, "unidad": "g", "familia": "carnes" },
      { "nombre": "judía verde plana", "cantidad": 200, "unidad": "g", "familia": "verduras" },
      { "nombre": "garrofón", "cantidad": 100, "unidad": "g", "familia": "legumbres" },
      { "nombre": "tomate triturado", "cantidad": 150, "unidad": "g", "familia": "verduras" },
      { "nombre": "pimentón dulce", "cantidad": 1, "unidad": "cdta", "familia": "especias" },
      { "nombre": "azafrán", "cantidad": 1, "unidad": "pizca", "familia": "especias" },
      { "nombre": "caldo de pollo", "cantidad": 1200, "unidad": "ml", "familia": "caldos" },
      { "nombre": "aceite de oliva", "cantidad": 60, "unidad": "ml", "familia": "aceites" }
    ],
    "pasos": [
      "Calienta el aceite en la paellera y sofríe el pollo y el conejo troceados hasta dorarlos bien.",
      "Añade las judías verdes y el garrofón, sofríe 5 minutos.",
      "Incorpora el tomate triturado y el pimentón, remueve rápido para que no se queme.",
      "Vierte el caldo caliente con el azafrán disuelto y lleva a ebullición.",
      "Añade el arroz en forma de cruz y repártelo sin remover.",
      "Cocina a fuego fuerte 8 minutos, luego baja el fuego y cocina 10 minutos más.",
      "Deja reposar 5 minutos tapado antes de servir."
    ]
  },
  {
    "id": "a1b2c3d4-0002-4000-8000-000000000002",
    "nombre": "Ramen de pollo",
    "categoria": "sopas",
    "sabor": "umami",
    "tiempoPreparacion": 50,
    "favorita": false,
    "imagen": "https://images.unsplash.com/photo-1569718212165-3a8278d5f624?w=800&q=80&crop=entropy",
    "ingredientes": [
      { "nombre": "fideos ramen", "cantidad": 200, "unidad": "g", "familia": "cereales" },
      { "nombre": "caldo de pollo", "cantidad": 1000, "unidad": "ml", "familia": "caldos" },
      { "nombre": "pechuga de pollo", "cantidad": 300, "unidad": "g", "familia": "carnes" },
      { "nombre": "salsa de soja", "cantidad": 40, "unidad": "ml", "familia": "salsas" },
      { "nombre": "miso blanco", "cantidad": 2, "unidad": "cda", "familia": "salsas" },
      { "nombre": "huevo", "cantidad": 2, "unidad": "ud", "familia": "huevos" },
      { "nombre": "cebolleta", "cantidad": 2, "unidad": "ud", "familia": "verduras" },
      { "nombre": "alga nori", "cantidad": 2, "unidad": "hoja", "familia": "otros" },
      { "nombre": "maíz dulce", "cantidad": 100, "unidad": "g", "familia": "verduras" },
      { "nombre": "jengibre fresco", "cantidad": 20, "unidad": "g", "familia": "especias" }
    ],
    "pasos": [
      "Cuece los huevos 7 minutos para que queden cremosos, pela y reserva.",
      "Calienta el caldo con el jengibre rallado, la soja y el miso.",
      "Pocha el pollo en el caldo a fuego suave durante 15 minutos, luego desmenuza.",
      "Cuece los fideos según el paquete y escúrrelos.",
      "Sirve los fideos en el caldo caliente y coloca encima el pollo, el huevo partido, el maíz, la cebolleta picada y el nori."
    ]
  },
  {
    "id": "a1b2c3d4-0003-4000-8000-000000000003",
    "nombre": "Gyozas de cerdo y col",
    "categoria": "asiática",
    "sabor": "umami",
    "tiempoPreparacion": 45,
    "favorita": false,
    "imagen": "https://images.unsplash.com/photo-1496116218417-1a781b1c416c?w=800&q=80&crop=entropy",
    "ingredientes": [
      { "nombre": "obleas de gyoza", "cantidad": 24, "unidad": "ud", "familia": "cereales" },
      { "nombre": "carne picada de cerdo", "cantidad": 300, "unidad": "g", "familia": "carnes" },
      { "nombre": "col china", "cantidad": 200, "unidad": "g", "familia": "verduras" },
      { "nombre": "cebolleta", "cantidad": 2, "unidad": "ud", "familia": "verduras" },
      { "nombre": "jengibre fresco", "cantidad": 15, "unidad": "g", "familia": "especias" },
      { "nombre": "salsa de soja", "cantidad": 20, "unidad": "ml", "familia": "salsas" },
      { "nombre": "aceite de sésamo", "cantidad": 10, "unidad": "ml", "familia": "aceites" }
    ],
    "pasos": [
      "Pica fina la col, sala y deja 10 minutos. Escurre bien apretando con las manos.",
      "Mezcla la carne con la col, la cebolleta, el jengibre rallado, la soja y el aceite de sésamo.",
      "Coloca una cucharada del relleno en el centro de cada oblea. Moja el borde con agua y cierra formando pliegues.",
      "Calienta aceite en una sartén antiadherente y dora las gyozas por la base 2 minutos.",
      "Añade 60 ml de agua, tapa y cocina al vapor 5 minutos.",
      "Destapa y deja que evapore el agua hasta que la base vuelva a crujir.",
      "Sirve con salsa de soja y vinagre de arroz."
    ]
  },
  {
    "id": "a1b2c3d4-0004-4000-8000-000000000004",
    "nombre": "Pad Thai de gambas",
    "categoria": "asiática",
    "sabor": "acido",
    "tiempoPreparacion": 25,
    "favorita": false,
    "imagen": "https://images.unsplash.com/photo-1559314809-0d155014e29e?w=800&q=80&crop=entropy",
    "ingredientes": [
      { "nombre": "fideos de arroz planos", "cantidad": 200, "unidad": "g", "familia": "cereales" },
      { "nombre": "gambas peladas", "cantidad": 250, "unidad": "g", "familia": "pescados" },
      { "nombre": "huevo", "cantidad": 2, "unidad": "ud", "familia": "huevos" },
      { "nombre": "brotes de soja", "cantidad": 150, "unidad": "g", "familia": "verduras" },
      { "nombre": "cebolleta", "cantidad": 3, "unidad": "ud", "familia": "verduras" },
      { "nombre": "salsa de tamarindo", "cantidad": 40, "unidad": "ml", "familia": "salsas" },
      { "nombre": "salsa de pescado", "cantidad": 30, "unidad": "ml", "familia": "salsas" },
      { "nombre": "azúcar de palma", "cantidad": 20, "unidad": "g", "familia": "dulces" },
      { "nombre": "cacahuetes tostados", "cantidad": 50, "unidad": "g", "familia": "frutos secos" },
      { "nombre": "lima", "cantidad": 1, "unidad": "ud", "familia": "frutas" }
    ],
    "pasos": [
      "Remoja los fideos en agua fría 30 minutos.",
      "Mezcla el tamarindo, la salsa de pescado y el azúcar para la salsa.",
      "Saltea las gambas en wok a fuego muy fuerte hasta que estén rosadas, retira.",
      "En el mismo wok, cuaja los huevos rápidamente y rómpelos.",
      "Añade los fideos escurridos y la salsa, saltea 2 minutos.",
      "Incorpora las gambas, los brotes de soja y la cebolleta.",
      "Sirve con cacahuetes picados y lima para exprimir."
    ]
  },
  {
    "id": "a1b2c3d4-0005-4000-8000-000000000005",
    "nombre": "Sopa de miso con tofu",
    "categoria": "sopas",
    "sabor": "umami",
    "tiempoPreparacion": 15,
    "favorita": false,
    "imagen": "https://images.unsplash.com/photo-1547592166-23ac45744acd?w=800&q=80&crop=entropy",
    "ingredientes": [
      { "nombre": "pasta de miso blanco", "cantidad": 3, "unidad": "cda", "familia": "salsas" },
      { "nombre": "tofu sedoso", "cantidad": 200, "unidad": "g", "familia": "proteínas" },
      { "nombre": "alga wakame seca", "cantidad": 10, "unidad": "g", "familia": "otros" },
      { "nombre": "caldo dashi", "cantidad": 800, "unidad": "ml", "familia": "caldos" },
      { "nombre": "cebolleta", "cantidad": 2, "unidad": "ud", "familia": "verduras" },
      { "nombre": "salsa de soja", "cantidad": 10, "unidad": "ml", "familia": "salsas" }
    ],
    "pasos": [
      "Hidrata el alga wakame en agua fría 5 minutos, escurre.",
      "Calienta el dashi a fuego suave sin que llegue a hervir.",
      "Disuelve el miso en un poco de caldo caliente y añádelo al resto.",
      "Incorpora el tofu cortado en dados pequeños y el wakame.",
      "Calienta 2 minutos sin hervir para que no se destruyan los probióticos del miso.",
      "Sirve con la cebolleta picada por encima."
    ]
  },
  {
    "id": "a1b2c3d4-0006-4000-8000-000000000006",
    "nombre": "Risotto de setas",
    "categoria": "arroces",
    "sabor": "umami",
    "tiempoPreparacion": 40,
    "favorita": false,
    "imagen": "https://images.unsplash.com/photo-1476124369491-e7addf5db371?w=800&q=80&crop=entropy",
    "ingredientes": [
      { "nombre": "arroz arborio", "cantidad": 320, "unidad": "g", "familia": "cereales" },
      { "nombre": "setas variadas", "cantidad": 400, "unidad": "g", "familia": "verduras" },
      { "nombre": "cebolla", "cantidad": 1, "unidad": "ud", "familia": "verduras" },
      { "nombre": "ajo", "cantidad": 2, "unidad": "dientes", "familia": "verduras" },
      { "nombre": "vino blanco seco", "cantidad": 120, "unidad": "ml", "familia": "bebidas" },
      { "nombre": "caldo de verduras", "cantidad": 1200, "unidad": "ml", "familia": "caldos" },
      { "nombre": "parmesano rallado", "cantidad": 80, "unidad": "g", "familia": "lácteos" },
      { "nombre": "mantequilla", "cantidad": 40, "unidad": "g", "familia": "lácteos" },
      { "nombre": "aceite de oliva", "cantidad": 30, "unidad": "ml", "familia": "aceites" }
    ],
    "pasos": [
      "Sofríe la cebolla y el ajo picados en aceite a fuego suave hasta que estén transparentes.",
      "Añade las setas y saltea a fuego fuerte hasta que evapore el agua.",
      "Incorpora el arroz y tuéstalo 2 minutos.",
      "Vierte el vino y remueve hasta que se absorba.",
      "Añade el caldo caliente cazo a cazo, removiendo constantemente y esperando que se absorba antes de añadir más.",
      "Fuera del fuego, añade la mantequilla y el parmesano. Remueve con energía y sirve inmediatamente."
    ]
  },
  {
    "id": "a1b2c3d4-0007-4000-8000-000000000007",
    "nombre": "Tiramisú",
    "categoria": "postres",
    "sabor": "amargo",
    "tiempoPreparacion": 30,
    "favorita": false,
    "imagen": "https://images.unsplash.com/photo-1571877227200-a0d98ea607e9?w=800&q=80&crop=entropy",
    "ingredientes": [
      { "nombre": "mascarpone", "cantidad": 500, "unidad": "g", "familia": "lácteos" },
      { "nombre": "huevos", "cantidad": 4, "unidad": "ud", "familia": "huevos" },
      { "nombre": "azúcar", "cantidad": 100, "unidad": "g", "familia": "dulces" },
      { "nombre": "bizcochos savoiardi", "cantidad": 24, "unidad": "ud", "familia": "cereales" },
      { "nombre": "café expreso", "cantidad": 300, "unidad": "ml", "familia": "bebidas" },
      { "nombre": "cacao en polvo", "cantidad": 30, "unidad": "g", "familia": "dulces" },
      { "nombre": "amaretto", "cantidad": 30, "unidad": "ml", "familia": "bebidas" }
    ],
    "pasos": [
      "Prepara el café y déjalo enfriar con el amaretto.",
      "Separa las yemas de las claras. Bate las yemas con el azúcar hasta que blanqueen.",
      "Incorpora el mascarpone a las yemas con movimientos envolventes.",
      "Monta las claras a punto de nieve e incorpóralas a la mezcla.",
      "Moja los bizcochos rápidamente en el café y colócalos en la base del molde.",
      "Extiende la mitad de la crema, otra capa de bizcochos y termina con crema.",
      "Refrigera mínimo 4 horas y espolvorea cacao antes de servir."
    ]
  },
  {
    "id": "a1b2c3d4-0008-4000-8000-000000000008",
    "nombre": "Fabada asturiana",
    "categoria": "legumbres",
    "sabor": "salado",
    "tiempoPreparacion": 120,
    "favorita": false,
    "imagen": "https://images.unsplash.com/photo-1547592180-85f173990554?w=800&q=80&crop=entropy",
    "ingredientes": [
      { "nombre": "fabes asturianas", "cantidad": 500, "unidad": "g", "familia": "legumbres" },
      { "nombre": "chorizo asturiano", "cantidad": 200, "unidad": "g", "familia": "carnes" },
      { "nombre": "morcilla asturiana", "cantidad": 200, "unidad": "g", "familia": "carnes" },
      { "nombre": "lacón", "cantidad": 200, "unidad": "g", "familia": "carnes" },
      { "nombre": "panceta curada", "cantidad": 150, "unidad": "g", "familia": "carnes" },
      { "nombre": "azafrán", "cantidad": 1, "unidad": "pizca", "familia": "especias" },
      { "nombre": "pimentón", "cantidad": 1, "unidad": "cdta", "familia": "especias" }
    ],
    "pasos": [
      "Pon las fabes a remojo en agua fría la noche anterior.",
      "Escurre y cubre con agua fría. Añade todas las carnes y lleva a ebullición.",
      "Espuma bien y baja el fuego. Cuece a fuego muy suave durante 2 horas.",
      "A mitad de cocción añade el azafrán disuelto en un poco de caldo caliente.",
      "Comprueba la sazón al final — las carnes ya aportan sal.",
      "Sirve en cazuela de barro con las carnes en rodajas."
    ]
  },
  {
    "id": "a1b2c3d4-0009-4000-8000-000000000009",
    "nombre": "Croquetas de jamón",
    "categoria": "tapas",
    "sabor": "salado",
    "tiempoPreparacion": 90,
    "favorita": false,
    "imagen": "https://images.unsplash.com/photo-1541529086526-db283c563270?w=800&q=80&crop=entropy",
    "ingredientes": [
      { "nombre": "jamón serrano", "cantidad": 150, "unidad": "g", "familia": "carnes" },
      { "nombre": "harina", "cantidad": 100, "unidad": "g", "familia": "cereales" },
      { "nombre": "mantequilla", "cantidad": 80, "unidad": "g", "familia": "lácteos" },
      { "nombre": "leche entera", "cantidad": 700, "unidad": "ml", "familia": "lácteos" },
      { "nombre": "nuez moscada", "cantidad": 1, "unidad": "pizca", "familia": "especias" },
      { "nombre": "huevo", "cantidad": 2, "unidad": "ud", "familia": "huevos" },
      { "nombre": "pan rallado", "cantidad": 150, "unidad": "g", "familia": "cereales" },
      { "nombre": "aceite de girasol", "cantidad": 500, "unidad": "ml", "familia": "aceites" }
    ],
    "pasos": [
      "Derrite la mantequilla y sofríe el jamón picado fino durante 2 minutos.",
      "Añade la harina y cocina 3 minutos removiendo para que no sepa a crudo.",
      "Incorpora la leche caliente poco a poco sin dejar de remover hasta obtener una bechamel espesa.",
      "Sazona con sal y nuez moscada, vierte en una fuente y deja enfriar en la nevera al menos 2 horas.",
      "Forma las croquetas, pásalas por huevo batido y pan rallado.",
      "Fríe en aceite bien caliente hasta que estén doradas."
    ]
  },
  {
    "id": "a1b2c3d4-0010-4000-8000-000000000010",
    "nombre": "Ensalada griega",
    "categoria": "ensaladas",
    "sabor": "acido",
    "tiempoPreparacion": 10,
    "favorita": false,
    "imagen": "https://images.unsplash.com/photo-1540189549336-e6e99c3679fe?w=800&q=80&crop=entropy",
    "ingredientes": [
      { "nombre": "tomate", "cantidad": 3, "unidad": "ud", "familia": "verduras" },
      { "nombre": "pepino", "cantidad": 1, "unidad": "ud", "familia": "verduras" },
      { "nombre": "cebolla roja", "cantidad": 1, "unidad": "ud", "familia": "verduras" },
      { "nombre": "queso feta", "cantidad": 200, "unidad": "g", "familia": "lácteos" },
      { "nombre": "aceitunas kalamata", "cantidad": 100, "unidad": "g", "familia": "otros" },
      { "nombre": "pimiento verde", "cantidad": 1, "unidad": "ud", "familia": "verduras" },
      { "nombre": "aceite de oliva virgen extra", "cantidad": 50, "unidad": "ml", "familia": "aceites" },
      { "nombre": "orégano seco", "cantidad": 1, "unidad": "cdta", "familia": "especias" },
      { "nombre": "vinagre de vino tinto", "cantidad": 20, "unidad": "ml", "familia": "ácidos" }
    ],
    "pasos": [
      "Corta los tomates en gajos gruesos y el pepino en medias lunas.",
      "Trocea la cebolla en aros finos y el pimiento en tiras.",
      "Coloca todo en una fuente. Añade las aceitunas y el feta en un bloque encima.",
      "Aliña con aceite de oliva, vinagre, orégano y sal.",
      "Sirve inmediatamente sin remover demasiado para que el feta se mantenga entero."
    ]
  },
  {
    "id": "a1b2c3d4-0011-4000-8000-000000000011",
    "nombre": "Hamburguesa smash",
    "categoria": "americana",
    "sabor": "salado",
    "tiempoPreparacion": 20,
    "favorita": false,
    "imagen": "https://images.unsplash.com/photo-1568901346375-23c9450c58cd?w=800&q=80&crop=entropy",
    "ingredientes": [
      { "nombre": "carne picada de ternera 80/20", "cantidad": 400, "unidad": "g", "familia": "carnes" },
      { "nombre": "panecillos brioche", "cantidad": 2, "unidad": "ud", "familia": "cereales" },
      { "nombre": "queso cheddar", "cantidad": 4, "unidad": "lonchas", "familia": "lácteos" },
      { "nombre": "cebolla", "cantidad": 1, "unidad": "ud", "familia": "verduras" },
      { "nombre": "lechuga", "cantidad": 4, "unidad": "hojas", "familia": "verduras" },
      { "nombre": "tomate", "cantidad": 1, "unidad": "ud", "familia": "verduras" },
      { "nombre": "mayonesa", "cantidad": 2, "unidad": "cda", "familia": "salsas" },
      { "nombre": "mostaza americana", "cantidad": 1, "unidad": "cda", "familia": "salsas" },
      { "nombre": "sal y pimienta", "cantidad": 1, "unidad": "al gusto", "familia": "especias" }
    ],
    "pasos": [
      "Forma bolas de 100 g con la carne sin aplastar todavía.",
      "Calienta una plancha de hierro a fuego muy fuerte hasta que humee.",
      "Coloca la bola y aplástala con una espátula firme hasta obtener una hamburguesa muy fina.",
      "Sazona con sal y pimienta. Cocina 2 minutos sin mover.",
      "Da la vuelta, coloca el queso y deja fundir 1 minuto.",
      "Tuesta el panecillo en la misma plancha. Monta con la salsa, la lechuga, el tomate y la cebolla."
    ]
  },
  {
    "id": "a1b2c3d4-0012-4000-8000-000000000012",
    "nombre": "Brownies de chocolate",
    "categoria": "postres",
    "sabor": "amargo",
    "tiempoPreparacion": 40,
    "favorita": false,
    "imagen": "https://images.unsplash.com/photo-1624353365286-3f8d62daad51?w=800&q=80&crop=entropy",
    "ingredientes": [
      { "nombre": "chocolate negro 70%", "cantidad": 200, "unidad": "g", "familia": "dulces" },
      { "nombre": "mantequilla", "cantidad": 120, "unidad": "g", "familia": "lácteos" },
      { "nombre": "huevos", "cantidad": 3, "unidad": "ud", "familia": "huevos" },
      { "nombre": "azúcar", "cantidad": 200, "unidad": "g", "familia": "dulces" },
      { "nombre": "harina", "cantidad": 80, "unidad": "g", "familia": "cereales" },
      { "nombre": "cacao en polvo", "cantidad": 30, "unidad": "g", "familia": "dulces" },
      { "nombre": "nueces", "cantidad": 100, "unidad": "g", "familia": "frutos secos" },
      { "nombre": "sal", "cantidad": 1, "unidad": "pizca", "familia": "especias" }
    ],
    "pasos": [
      "Precalienta el horno a 175°C. Forra un molde cuadrado de 20 cm con papel de horno.",
      "Funde el chocolate con la mantequilla al baño maría. Deja templar.",
      "Bate los huevos con el azúcar hasta que blanqueen y doblen su volumen.",
      "Incorpora el chocolate fundido a los huevos con movimientos envolventes.",
      "Tamiza la harina, el cacao y la sal sobre la mezcla e integra sin sobremezclar.",
      "Añade las nueces, vierte en el molde y hornea 25 minutos. El centro debe quedar ligeramente húmedo."
    ]
  },
  {
    "id": "a1b2c3d4-0013-4000-8000-000000000013",
    "nombre": "Macarons de frambuesa",
    "categoria": "postres",
    "sabor": "dulce",
    "tiempoPreparacion": 60,
    "favorita": false,
    "imagen": "https://images.unsplash.com/photo-1470124182917-cc6e71b22ecc?w=800&q=80&crop=entropy",
    "ingredientes": [
      { "nombre": "almendra molida tamizada", "cantidad": 125, "unidad": "g", "familia": "frutos secos" },
      { "nombre": "azúcar glas tamizado", "cantidad": 225, "unidad": "g", "familia": "dulces" },
      { "nombre": "claras de huevo envejecidas", "cantidad": 100, "unidad": "g", "familia": "huevos" },
      { "nombre": "azúcar", "cantidad": 75, "unidad": "g", "familia": "dulces" },
      { "nombre": "colorante rojo", "cantidad": 2, "unidad": "gotas", "familia": "otros" },
      { "nombre": "frambuesas", "cantidad": 150, "unidad": "g", "familia": "frutas" },
      { "nombre": "nata para montar", "cantidad": 100, "unidad": "ml", "familia": "lácteos" },
      { "nombre": "chocolate blanco", "cantidad": 100, "unidad": "g", "familia": "dulces" }
    ],
    "pasos": [
      "Mezcla la almendra molida con el azúcar glas (tant pour tant) y tamiza dos veces.",
      "Monta las claras a punto de nieve firme añadiendo el azúcar poco a poco.",
      "Añade el colorante y aplica el macaronage: mezcla con espátula hasta que caiga en cinta.",
      "Escudilla círculos de 3,5 cm en bandejas con papel de horno. Deja reposar 30 minutos.",
      "Hornea a 145°C durante 14 minutos. Deja enfriar completamente.",
      "Para el ganache: calienta la nata, vierte sobre el chocolate troceado, mezcla. Deja enfriar y monta.",
      "Añade las frambuesas trituradas al ganache. Rellena los macarons y deja reposar 24 horas en nevera."
    ]
  },
  {
    "id": "a1b2c3d4-0014-4000-8000-000000000014",
    "nombre": "Tarta de zanahoria",
    "categoria": "postres",
    "sabor": "dulce",
    "tiempoPreparacion": 55,
    "favorita": false,
    "imagen": "https://images.unsplash.com/photo-1621303837174-89787a7d4729?w=800&q=80&crop=entropy",
    "ingredientes": [
      { "nombre": "zanahoria rallada", "cantidad": 300, "unidad": "g", "familia": "verduras" },
      { "nombre": "harina", "cantidad": 250, "unidad": "g", "familia": "cereales" },
      { "nombre": "azúcar moreno", "cantidad": 200, "unidad": "g", "familia": "dulces" },
      { "nombre": "aceite de girasol", "cantidad": 180, "unidad": "ml", "familia": "aceites" },
      { "nombre": "huevos", "cantidad": 3, "unidad": "ud", "familia": "huevos" },
      { "nombre": "canela molida", "cantidad": 2, "unidad": "cdta", "familia": "especias" },
      { "nombre": "nuez moscada", "cantidad": 0.5, "unidad": "cdta", "familia": "especias" },
      { "nombre": "levadura", "cantidad": 1.5, "unidad": "cdta", "familia": "cereales" },
      { "nombre": "queso crema", "cantidad": 300, "unidad": "g", "familia": "lácteos" },
      { "nombre": "azúcar glas", "cantidad": 150, "unidad": "g", "familia": "dulces" }
    ],
    "pasos": [
      "Precalienta el horno a 180°C. Engrasa dos moldes redondos de 20 cm.",
      "Bate los huevos con el azúcar y el aceite hasta integrar.",
      "Tamiza la harina, la levadura, la canela y la nuez moscada sobre la mezcla.",
      "Incorpora la zanahoria rallada y mezcla hasta obtener una masa homogénea.",
      "Reparte en los moldes y hornea 30-35 minutos. Enfría completamente.",
      "Para el frosting: bate el queso crema con el azúcar glas hasta obtener una crema suave.",
      "Rellena y cubre la tarta con el frosting de queso crema."
    ]
  },
  {
    "id": "a1b2c3d4-0015-4000-8000-000000000015",
    "nombre": "Mousse de chocolate negro",
    "categoria": "postres",
    "sabor": "amargo",
    "tiempoPreparacion": 25,
    "favorita": false,
    "imagen": "https://images.unsplash.com/photo-1511381939415-e44015466834?w=800&q=80&crop=entropy",
    "ingredientes": [
      { "nombre": "chocolate negro 70%", "cantidad": 200, "unidad": "g", "familia": "dulces" },
      { "nombre": "huevos", "cantidad": 4, "unidad": "ud", "familia": "huevos" },
      { "nombre": "azúcar", "cantidad": 60, "unidad": "g", "familia": "dulces" },
      { "nombre": "mantequilla", "cantidad": 30, "unidad": "g", "familia": "lácteos" },
      { "nombre": "nata para montar", "cantidad": 200, "unidad": "ml", "familia": "lácteos" },
      { "nombre": "sal", "cantidad": 1, "unidad": "pizca", "familia": "especias" }
    ],
    "pasos": [
      "Funde el chocolate con la mantequilla al baño maría y deja templar.",
      "Separa yemas y claras. Bate las yemas con la mitad del azúcar hasta blanquear e incorpora al chocolate.",
      "Monta la nata y resérala en la nevera.",
      "Monta las claras con el resto del azúcar y una pizca de sal a punto de nieve firme.",
      "Incorpora la nata al chocolate con movimientos envolventes, luego las claras en tres veces.",
      "Reparte en copas y refrigera mínimo 3 horas."
    ]
  },
  {
    "id": "a1b2c3d4-0016-4000-8000-000000000016",
    "nombre": "Leche frita",
    "categoria": "postres",
    "sabor": "dulce",
    "tiempoPreparacion": 40,
    "favorita": false,
    "imagen": "https://images.unsplash.com/photo-1551024506-0bccd828d307?w=800&q=80&crop=entropy",
    "ingredientes": [
      { "nombre": "leche entera", "cantidad": 600, "unidad": "ml", "familia": "lácteos" },
      { "nombre": "harina", "cantidad": 80, "unidad": "g", "familia": "cereales" },
      { "nombre": "maicena", "cantidad": 40, "unidad": "g", "familia": "cereales" },
      { "nombre": "azúcar", "cantidad": 120, "unidad": "g", "familia": "dulces" },
      { "nombre": "canela en rama", "cantidad": 1, "unidad": "ud", "familia": "especias" },
      { "nombre": "piel de limón", "cantidad": 1, "unidad": "tira", "familia": "frutas" },
      { "nombre": "huevo", "cantidad": 2, "unidad": "ud", "familia": "huevos" },
      { "nombre": "aceite de girasol", "cantidad": 300, "unidad": "ml", "familia": "aceites" },
      { "nombre": "canela molida y azúcar para rebozar", "cantidad": 50, "unidad": "g", "familia": "dulces" }
    ],
    "pasos": [
      "Infusiona la leche con la canela en rama y la piel de limón. Retira y cuela.",
      "Mezcla la harina, maicena y azúcar con un poco de leche fría hasta disolver.",
      "Añade el resto de la leche caliente poco a poco y cuece a fuego suave removiendo hasta que espese mucho.",
      "Vierte en una bandeja engrasada de 2 cm de grosor. Refrigera 3 horas.",
      "Corta en rectángulos, pasa por huevo batido y fríe hasta dorar.",
      "Reboza en azúcar con canela molida y sirve caliente."
    ]
  },
  {
    "id": "a1b2c3d4-0017-4000-8000-000000000017",
    "nombre": "Tacos de pollo al pastor",
    "categoria": "mexicana",
    "sabor": "salado",
    "tiempoPreparacion": 35,
    "favorita": false,
    "imagen": "https://images.unsplash.com/photo-1565299585323-38d6b0865b47?w=800&q=80&crop=entropy",
    "ingredientes": [
      { "nombre": "pechuga de pollo", "cantidad": 500, "unidad": "g", "familia": "carnes" },
      { "nombre": "tortillas de maíz", "cantidad": 8, "unidad": "ud", "familia": "cereales" },
      { "nombre": "chile guajillo seco", "cantidad": 3, "unidad": "ud", "familia": "especias" },
      { "nombre": "piña en rodajas", "cantidad": 150, "unidad": "g", "familia": "frutas" },
      { "nombre": "cebolla", "cantidad": 1, "unidad": "ud", "familia": "verduras" },
      { "nombre": "cilantro fresco", "cantidad": 20, "unidad": "g", "familia": "hierbas" },
      { "nombre": "ajo", "cantidad": 2, "unidad": "dientes", "familia": "verduras" },
      { "nombre": "vinagre de manzana", "cantidad": 30, "unidad": "ml", "familia": "ácidos" },
      { "nombre": "achiote en pasta", "cantidad": 1, "unidad": "cda", "familia": "especias" },
      { "nombre": "lima", "cantidad": 2, "unidad": "ud", "familia": "frutas" }
    ],
    "pasos": [
      "Hidrata los chiles en agua caliente 20 minutos. Escurre y tritura con el ajo, el achiote y el vinagre.",
      "Marina el pollo en la salsa roja durante al menos 2 horas.",
      "Asa el pollo en plancha o parrilla a fuego fuerte hasta que esté bien dorado. Reposa 5 minutos y pica.",
      "Calienta las tortillas en comal o sartén seca.",
      "Asa la piña en la plancha hasta que caramelice.",
      "Monta los tacos con el pollo, la piña, la cebolla picada y el cilantro. Sirve con lima."
    ]
  },
  {
    "id": "a1b2c3d4-0018-4000-8000-000000000018",
    "nombre": "Sushi rolls de salmón",
    "categoria": "asiática",
    "sabor": "umami",
    "tiempoPreparacion": 45,
    "favorita": false,
    "imagen": "https://images.unsplash.com/photo-1617196034183-421b4040ed20?w=800&q=80&crop=entropy",
    "ingredientes": [
      { "nombre": "arroz para sushi", "cantidad": 300, "unidad": "g", "familia": "cereales" },
      { "nombre": "salmón fresco para sashimi", "cantidad": 200, "unidad": "g", "familia": "pescados" },
      { "nombre": "hojas de nori", "cantidad": 4, "unidad": "ud", "familia": "otros" },
      { "nombre": "vinagre de arroz", "cantidad": 50, "unidad": "ml", "familia": "ácidos" },
      { "nombre": "azúcar", "cantidad": 20, "unidad": "g", "familia": "dulces" },
      { "nombre": "sal", "cantidad": 5, "unidad": "g", "familia": "especias" },
      { "nombre": "aguacate", "cantidad": 1, "unidad": "ud", "familia": "frutas" },
      { "nombre": "pepino", "cantidad": 0.5, "unidad": "ud", "familia": "verduras" },
      { "nombre": "salsa de soja", "cantidad": 50, "unidad": "ml", "familia": "salsas" },
      { "nombre": "wasabi", "cantidad": 1, "unidad": "cdta", "familia": "especias" }
    ],
    "pasos": [
      "Lava el arroz hasta que el agua salga clara. Cuece con la misma cantidad de agua, tapa y cuece 12 minutos. Reposa 10 minutos.",
      "Mezcla el vinagre, el azúcar y la sal hasta disolver. Incorpora al arroz caliente con movimientos de corte. Abanica para enfriar.",
      "Corta el salmón, el aguacate y el pepino en tiras.",
      "Coloca el nori en la esterilla, extiende una capa fina de arroz dejando 2 cm en el extremo.",
      "Coloca el relleno en el centro y enrolla con firmeza usando la esterilla.",
      "Moja el cuchillo y corta en 8 piezas. Sirve con soja y wasabi."
    ]
  },
  {
    "id": "a1b2c3d4-0019-4000-8000-000000000019",
    "nombre": "Pizza margherita",
    "categoria": "italiana",
    "sabor": "salado",
    "tiempoPreparacion": 90,
    "favorita": false,
    "imagen": "https://images.unsplash.com/photo-1574071318508-1cdbab80d002?w=800&q=80&crop=entropy",
    "ingredientes": [
      { "nombre": "harina de fuerza W300", "cantidad": 500, "unidad": "g", "familia": "cereales" },
      { "nombre": "agua tibia", "cantidad": 325, "unidad": "ml", "familia": "otros" },
      { "nombre": "levadura seca", "cantidad": 3, "unidad": "g", "familia": "cereales" },
      { "nombre": "sal", "cantidad": 10, "unidad": "g", "familia": "especias" },
      { "nombre": "tomates san marzano", "cantidad": 400, "unidad": "g", "familia": "verduras" },
      { "nombre": "mozzarella fior di latte", "cantidad": 300, "unidad": "g", "familia": "lácteos" },
      { "nombre": "hojas de albahaca fresca", "cantidad": 10, "unidad": "ud", "familia": "hierbas" },
      { "nombre": "aceite de oliva virgen extra", "cantidad": 30, "unidad": "ml", "familia": "aceites" }
    ],
    "pasos": [
      "Disuelve la levadura en el agua. Mezcla con la harina y la sal hasta obtener una masa. Amasa 10 minutos.",
      "Deja fermentar en un bol tapado 24 horas en la nevera.",
      "Saca la masa 2 horas antes. Divide en dos bolas y deja reposar.",
      "Precalienta el horno al máximo (250°C o más) con la bandeja dentro.",
      "Tritura los tomates a mano con sal. Estira la masa a mano desde el centro hacia fuera.",
      "Añade la salsa de tomate, la mozzarella desmenuzada y hornea 8-10 minutos.",
      "Termina con las hojas de albahaca fresca y un hilo de aceite."
    ]
  },
  {
    "id": "a1b2c3d4-0020-4000-8000-000000000020",
    "nombre": "Curry de garbanzos y espinacas",
    "categoria": "india",
    "sabor": "salado",
    "tiempoPreparacion": 30,
    "favorita": false,
    "imagen": "https://images.unsplash.com/photo-1565557623262-b51c2513a641?w=800&q=80&crop=entropy",
    "ingredientes": [
      { "nombre": "garbanzos cocidos", "cantidad": 400, "unidad": "g", "familia": "legumbres" },
      { "nombre": "espinacas frescas", "cantidad": 200, "unidad": "g", "familia": "verduras" },
      { "nombre": "tomates triturados", "cantidad": 400, "unidad": "g", "familia": "verduras" },
      { "nombre": "cebolla", "cantidad": 1, "unidad": "ud", "familia": "verduras" },
      { "nombre": "ajo", "cantidad": 3, "unidad": "dientes", "familia": "verduras" },
      { "nombre": "jengibre fresco", "cantidad": 20, "unidad": "g", "familia": "especias" },
      { "nombre": "leche de coco", "cantidad": 200, "unidad": "ml", "familia": "lácteos" },
      { "nombre": "curry en polvo", "cantidad": 2, "unidad": "cda", "familia": "especias" },
      { "nombre": "garam masala", "cantidad": 1, "unidad": "cdta", "familia": "especias" },
      { "nombre": "aceite de girasol", "cantidad": 30, "unidad": "ml", "familia": "aceites" }
    ],
    "pasos": [
      "Sofríe la cebolla en aceite a fuego medio hasta que esté dorada, unos 8 minutos.",
      "Añade el ajo y el jengibre rallados, cocina 2 minutos.",
      "Incorpora el curry y el garam masala, tuesta 1 minuto sin dejar de remover.",
      "Añade el tomate triturado y cocina 5 minutos hasta que reduzca.",
      "Incorpora los garbanzos y la leche de coco. Cuece 10 minutos a fuego suave.",
      "Añade las espinacas al final y remueve hasta que se marchiten. Ajusta de sal y sirve con arroz basmati."
    ]
  }
]
